[
    {
        "class": "product_like",
        "id": "2885158:100004069",
        "owner": {
            "class": "uid",
            "id": "100004069",
            "owner": null,
            "parent": null,
            "label": "*～花音～*",
            "description": "",
            "image": {
                "url": "https://fitter.cosme.net/images/user/characters/150/mychara09_xl.gif"
            },
            "url": "https://www.cosme.net/user/100004069",
            "extras": {
                "coverImage": {
                    "url": "https://fitter.cosme.net/images/user/covers/mycover_makeup.jpg"
                }
            },
            "createdAt":"2000-03-23
14: 59: 58","updatedAt":"2017-12-25 13: 51: 54","publishedAt":"2017-12-19 14: 35: 41","expiredAt":"0000-00-00
00: 00: 00"},"parent":{"class":"product","id":"2885158","owner":null,"parent":{"class":"brand","id":"515","owner":null,"parent":null,"label":"ビューティーネイラー","description":"","image":{"url":""},"url":"https: //www.cosme.net/brand/brand_id/515/top/nt","extras":{"hasContract":false},"createdAt":"2000-03-27
            13: 20: 25","updatedAt":"2010-09-15 09: 50: 57","publishedAt":"2000-03-27 13: 20: 25","expiredAt":"0000-00-00
00: 00: 00"},"label":"アイラッシュバリューパック","description":"ボリュームと長さをアップしてインパクトのある目元に仕上げます。つけまつ毛が５ペア入ったバリューパック。水洗いしてくり返し使えます。\r\n【セット内容】\r\nつけまつ毛×5ペア\r\nまつげ強力接着剤×1本\r\n単品サイズ：縦142×横幅85×奥行14(mm)","image":{"url":"https: //fitter.cosme.net/media/product/2885/skuimg_753333_xl.jpg"},"url":"https://www.cosme.net/product/product_id/2885158/top","extras":{"categories":[{"id":"1114","label":"つけまつげ"}]},"createdAt":"2005-12-19
            23: 46: 50","updatedAt":"2020-03-27 13: 40: 38","publishedAt":"2020-03-27 13: 41: 09","expiredAt":"0000-00-00
00: 00: 00"},"label":"","description":"","image":{"url":""},"url":"https: //www.cosme.net/product/product_id/2885158/top","extras":{},"createdAt":"2011-08-24
            04: 22: 04","updatedAt":"2011-08-24 04: 22: 04","publishedAt":"2011-08-24 04: 22: 04","expiredAt":"0000-00-00
00: 00: 00"},{"class":"product_like","id":"2885158: 100009937","owner":{"class":"uid","id":"100009937","owner":null,"parent":null,"label":"あゆか","description":"","image":{"url":"https: //fitter.cosme.net/images/user/characters/150/mychara04_xl.gif"},"url":"https://www.cosme.net/user/100009937","extras":{"coverImage":{"url":"https://fitter.cosme.net/images/user/covers/mycover_nail.jpg"}},"createdAt":"2000-06-29
            19: 53: 32","updatedAt":"2020-03-04 22: 24: 07","publishedAt":"2018-03-13 12: 03: 23","expiredAt":"0000-00-00
00: 00: 00"},"parent":{"class":"product","id":"2885158","owner":null,"parent":{"class":"brand","id":"515","owner":null,"parent":null,"label":"ビューティーネイラー","description":"","image":{"url":""},"url":"https: //www.cosme.net/brand/brand_id/515/top/nt","extras":{"hasContract":false},"createdAt":"2000-03-27
            13: 20: 25","updatedAt":"2010-09-15 09: 50: 57","publishedAt":"2000-03-27 13: 20: 25","expiredAt":"0000-00-00
00: 00: 00"},"label":"アイラッシュバリューパック","description":"ボリュームと長さをアップしてインパクトのある目元に仕上げます。つけまつ毛が５ペア入ったバリューパック。水洗いしてくり返し使えます。\r\n【セット内容】\r\nつけまつ毛×5ペア\r\nまつげ強力接着剤×1本\r\n単品サイズ：縦142×横幅85×奥行14(mm)","image":{"url":"https: //fitter.cosme.net/media/product/2885/skuimg_753333_xl.jpg"},"url":"https://www.cosme.net/product/product_id/2885158/top","extras":{"categories":[{"id":"1114","label":"つけまつげ"}]},"createdAt":"2005-12-19
            23: 46: 50","updatedAt":"2020-03-27 13: 40: 38","publishedAt":"2020-03-27 13: 41: 09","expiredAt":"0000-00-00
00: 00: 00"},"label":"","description":"","image":{"url":""},"url":"https: //www.cosme.net/product/product_id/2885158/top","extras":{},"createdAt":"2011-08-30
            23: 16: 38","updatedAt":"2011-08-30 23: 16: 38","publishedAt":"2011-08-30 23: 16: 38","expiredAt":"0000-00-00
00: 00: 00"},{"class":"product_like","id":"2885158: 100014608","owner":{"class":"uid","id":"100014608","owner":null,"parent":null,"label":"よねりん","description":"","image":{"url":"https: //fitter.cosme.net/images/user/characters/150/mychara09_xl.gif"},"url":"https://www.cosme.net/user/100014608","extras":{"coverImage":{"url":"https://fitter.cosme.net/images/user/covers/mycover_bath.jpg"}},"createdAt":"2000-08-18
            21: 30: 41","updatedAt":"2017-12-19 13: 16: 12","publishedAt":"2017-12-19 13: 16: 12","expiredAt":"0000-00-00
00: 00: 00"},"parent":{"class":"product","id":"2885158","owner":null,"parent":{"class":"brand","id":"515","owner":null,"parent":null,"label":"ビューティーネイラー","description":"","image":{"url":""},"url":"https: //www.cosme.net/brand/brand_id/515/top/nt","extras":{"hasContract":false},"createdAt":"2000-03-27
            13: 20: 25","updatedAt":"2010-09-15 09: 50: 57","publishedAt":"2000-03-27 13: 20: 25","expiredAt":"0000-00-00
00: 00: 00"},"label":"アイラッシュバリューパック","description":"ボリュームと長さをアップしてインパクトのある目元に仕上げます。つけまつ毛が５ペア入ったバリューパック。水洗いしてくり返し使えます。\r\n【セット内容】\r\nつけまつ毛×5ペア\r\nまつげ強力接着剤×1本\r\n単品サイズ：縦142×横幅85×奥行14(mm)","image":{"url":"https: //fitter.cosme.net/media/product/2885/skuimg_753333_xl.jpg"},"url":"https://www.cosme.net/product/product_id/2885158/top","extras":{"categories":[{"id":"1114","label":"つけまつげ"}]},"createdAt":"2005-12-19
            23: 46: 50","updatedAt":"2020-03-27 13: 40: 38","publishedAt":"2020-03-27 13: 41: 09","expiredAt":"0000-00-00
00: 00: 00"},"label":"","description":"","image":{"url":""},"url":"https: //www.cosme.net/product/product_id/2885158/top","extras":{},"createdAt":"2011-05-20
            17: 43: 35","updatedAt":"2011-05-20 17: 43: 35","publishedAt":"2011-05-20 17: 43: 35","expiredAt":"0000-00-00
00: 00: 00"},{"class":"product_like","id":"2885158: 100020518","owner":{"class":"uid","id":"100020518","owner":null,"parent":null,"label":"由紀","description":"","image":{"url":"https: //fitter.cosme.net/media/collection/5/38/1988623.jpg"},"url":"https://www.cosme.net/user/100020518","extras":{"coverImage":{"url":"https://fitter.cosme.net/images/user/covers/mycover_makeup.jpg"}},"createdAt":"2000-09-28
            17: 49: 56","updatedAt":"2021-09-27 11: 51: 45","publishedAt":"2000-09-28 17: 49: 56","expiredAt":"0000-00-00
00: 00: 00"},"parent":{"class":"product","id":"2885158","owner":null,"parent":{"class":"brand","id":"515","owner":null,"parent":null,"label":"ビューティーネイラー","description":"","image":{"url":""},"url":"https: //www.cosme.net/brand/brand_id/515/top/nt","extras":{"hasContract":false},"createdAt":"2000-03-27
            13: 20: 25","updatedAt":"2010-09-15 09: 50: 57","publishedAt":"2000-03-27 13: 20: 25","expiredAt":"0000-00-00
00: 00: 00"},"label":"アイラッシュバリューパック","description":"ボリュームと長さをアップしてインパクトのある目元に仕上げます。つけまつ毛が５ペア入ったバリューパック。水洗いしてくり返し使えます。\r\n【セット内容】\r\nつけまつ毛×5ペア\r\nまつげ強力接着剤×1本\r\n単品サイズ：縦142×横幅85×奥行14(mm)","image":{"url":"https: //fitter.cosme.net/media/product/2885/skuimg_753333_xl.jpg"},"url":"https://www.cosme.net/product/product_id/2885158/top","extras":{"categories":[{"id":"1114","label":"つけまつげ"}]},"createdAt":"2005-12-19
            23: 46: 50","updatedAt":"2020-03-27 13: 40: 38","publishedAt":"2020-03-27 13: 41: 09","expiredAt":"0000-00-00
00: 00: 00"},"label":"","description":"","image":{"url":""},"url":"https: //www.cosme.net/product/product_id/2885158/top","extras":{},"createdAt":"2010-10-07
            06: 52: 52","updatedAt":"2010-10-07 06: 52: 52","publishedAt":"2010-10-07 06: 52: 52","expiredAt":"0000-00-00
00: 00: 00"},{"class":"product_like","id":"2885158: 100037628","owner":{"class":"uid","id":"100037628","owner":null,"parent":null,"label":"shikako","description":"","image":{"url":"https: //fitter.cosme.net/images/user/characters/150/mychara08_xl.gif"},"url":"https://www.cosme.net/user/100037628","extras":{"coverImage":{"url":"https://fitter.cosme.net/images/user/covers/mycover_skincare.jpg"}},"createdAt":"2001-03-23
            10: 34: 50","updatedAt":"2018-05-24 20: 58: 40","publishedAt":"2018-05-24 20: 58: 40","expiredAt":"0000-00-00
00: 00: 00"},"parent":{"class":"product","id":"2885158","owner":null,"parent":{"class":"brand","id":"515","owner":null,"parent":null,"label":"ビューティーネイラー","description":"","image":{"url":""},"url":"https: //www.cosme.net/brand/brand_id/515/top/nt","extras":{"hasContract":false},"createdAt":"2000-03-27
            13: 20: 25","updatedAt":"2010-09-15 09: 50: 57","publishedAt":"2000-03-27 13: 20: 25","expiredAt":"0000-00-00
00: 00: 00"},"label":"アイラッシュバリューパック","description":"ボリュームと長さをアップしてインパクトのある目元に仕上げます。つけまつ毛が５ペア入ったバリューパック。水洗いしてくり返し使えます。\r\n【セット内容】\r\nつけまつ毛×5ペア\r\nまつげ強力接着剤×1本\r\n単品サイズ：縦142×横幅85×奥行14(mm)","image":{"url":"https: //fitter.cosme.net/media/product/2885/skuimg_753333_xl.jpg"},"url":"https://www.cosme.net/product/product_id/2885158/top","extras":{"categories":[{"id":"1114","label":"つけまつげ"}]},"createdAt":"2005-12-19
            23: 46: 50","updatedAt":"2020-03-27 13: 40: 38","publishedAt":"2020-03-27 13: 41: 09","expiredAt":"0000-00-00
00: 00: 00"},"label":"","description":"","image":{"url":""},"url":"https: //www.cosme.net/product/product_id/2885158/top","extras":{},"createdAt":"2012-05-20
            19: 12: 23","updatedAt":"2012-05-20 19: 12: 23","publishedAt":"2012-05-20 19: 12: 23","expiredAt":"0000-00-00
00: 00: 00"},{"class":"product_like","id":"2885158: 100049352","owner":{"class":"uid","id":"100049352","owner":null,"parent":null,"label":"ぷくのん","description":"","image":{"url":"https: //fitter.cosme.net/images/user/characters/150/mychara26_xl.gif"},"url":"https://www.cosme.net/user/100049352","extras":{"coverImage":{"url":"https://fitter.cosme.net/images/user/covers/mycover_skincare.jpg"}},"createdAt":"2001-05-31
            15: 07: 16","updatedAt":"2017-12-23 10: 29: 52","publishedAt":"2017-12-23 10: 29: 52","expiredAt":"0000-00-00
00: 00: 00"},"parent":{"class":"product","id":"2885158","owner":null,"parent":{"class":"brand","id":"515","owner":null,"parent":null,"label":"ビューティーネイラー","description":"","image":{"url":""},"url":"https: //www.cosme.net/brand/brand_id/515/top/nt","extras":{"hasContract":false},"createdAt":"2000-03-27
            13: 20: 25","updatedAt":"2010-09-15 09: 50: 57","publishedAt":"2000-03-27 13: 20: 25","expiredAt":"0000-00-00
00: 00: 00"},"label":"アイラッシュバリューパック","description":"ボリュームと長さをアップしてインパクトのある目元に仕上げます。つけまつ毛が５ペア入ったバリューパック。水洗いしてくり返し使えます。\r\n【セット内容】\r\nつけまつ毛×5ペア\r\nまつげ強力接着剤×1本\r\n単品サイズ：縦142×横幅85×奥行14(mm)","image":{"url":"https: //fitter.cosme.net/media/product/2885/skuimg_753333_xl.jpg"},"url":"https://www.cosme.net/product/product_id/2885158/top","extras":{"categories":[{"id":"1114","label":"つけまつげ"}]},"createdAt":"2005-12-19
            23: 46: 50","updatedAt":"2020-03-27 13: 40: 38","publishedAt":"2020-03-27 13: 41: 09","expiredAt":"0000-00-00
00: 00: 00"},"label":"","description":"","image":{"url":""},"url":"https: //www.cosme.net/product/product_id/2885158/top","extras":{},"createdAt":"2011-10-11
            10: 45: 09","updatedAt":"2011-10-11 10: 45: 09","publishedAt":"2011-10-11 10: 45: 09","expiredAt":"0000-00-00
00: 00: 00"},{"class":"product_like","id":"2885158: 100049608","owner":{"class":"uid","id":"100049608","owner":null,"parent":null,"label":"みんみんみん","description":"","image":{"url":"https: //fitter.cosme.net/images/user/characters/150/mychara03_xl.gif"},"url":"https://www.cosme.net/user/100049608","extras":{"coverImage":{"url":"https://fitter.cosme.net/images/user/covers/mycover_makeup.jpg"}},"createdAt":"2001-06-02
            18: 21: 05","updatedAt":"2017-12-20 19: 23: 27","publishedAt":"2017-12-20 19: 23: 27","expiredAt":"0000-00-00
00: 00: 00"},"parent":{"class":"product","id":"2885158","owner":null,"parent":{"class":"brand","id":"515","owner":null,"parent":null,"label":"ビューティーネイラー","description":"","image":{"url":""},"url":"https: //www.cosme.net/brand/brand_id/515/top/nt","extras":{"hasContract":false},"createdAt":"2000-03-27
            13: 20: 25","updatedAt":"2010-09-15 09: 50: 57","publishedAt":"2000-03-27 13: 20: 25","expiredAt":"0000-00-00
00: 00: 00"},"label":"アイラッシュバリューパック","description":"ボリュームと長さをアップしてインパクトのある目元に仕上げます。つけまつ毛が５ペア入ったバリューパック。水洗いしてくり返し使えます。\r\n【セット内容】\r\nつけまつ毛×5ペア\r\nまつげ強力接着剤×1本\r\n単品サイズ：縦142×横幅85×奥行14(mm)","image":{"url":"https: //fitter.cosme.net/media/product/2885/skuimg_753333_xl.jpg"},"url":"https://www.cosme.net/product/product_id/2885158/top","extras":{"categories":[{"id":"1114","label":"つけまつげ"}]},"createdAt":"2005-12-19
            23: 46: 50","updatedAt":"2020-03-27 13: 40: 38","publishedAt":"2020-03-27 13: 41: 09","expiredAt":"0000-00-00
00: 00: 00"},"label":"","description":"","image":{"url":""},"url":"https: //www.cosme.net/product/product_id/2885158/top","extras":{},"createdAt":"2011-01-09
            15: 20: 48","updatedAt":"2011-01-09 15: 20: 48","publishedAt":"2011-01-09 15: 20: 48","expiredAt":"0000-00-00
00: 00: 00"},{"class":"product_like","id":"2885158: 100050321","owner":{"class":"uid","id":"100050321","owner":null,"parent":null,"label":"にゃんもも","description":"","image":{"url":"https: //fitter.cosme.net/images/user/characters/150/mychara09_xl.gif"},"url":"https://www.cosme.net/user/100050321","extras":{"coverImage":{"url":"https://fitter.cosme.net/images/user/covers/mycover_hair.jpg"}},"createdAt":"2001-06-07
            21: 55: 20","updatedAt":"2017-12-23 02: 36: 05","publishedAt":"2017-12-23 02: 36: 05","expiredAt":"0000-00-00
00: 00: 00"},"parent":{"class":"product","id":"2885158","owner":null,"parent":{"class":"brand","id":"515","owner":null,"parent":null,"label":"ビューティーネイラー","description":"","image":{"url":""},"url":"https: //www.cosme.net/brand/brand_id/515/top/nt","extras":{"hasContract":false},"createdAt":"2000-03-27
            13: 20: 25","updatedAt":"2010-09-15 09: 50: 57","publishedAt":"2000-03-27 13: 20: 25","expiredAt":"0000-00-00
00: 00: 00"},"label":"アイラッシュバリューパック","description":"ボリュームと長さをアップしてインパクトのある目元に仕上げます。つけまつ毛が５ペア入ったバリューパック。水洗いしてくり返し使えます。\r\n【セット内容】\r\nつけまつ毛×5ペア\r\nまつげ強力接着剤×1本\r\n単品サイズ：縦142×横幅85×奥行14(mm)","image":{"url":"https: //fitter.cosme.net/media/product/2885/skuimg_753333_xl.jpg"},"url":"https://www.cosme.net/product/product_id/2885158/top","extras":{"categories":[{"id":"1114","label":"つけまつげ"}]},"createdAt":"2005-12-19
            23: 46: 50","updatedAt":"2020-03-27 13: 40: 38","publishedAt":"2020-03-27 13: 41: 09","expiredAt":"0000-00-00
00: 00: 00"},"label":"","description":"","image":{"url":""},"url":"https: //www.cosme.net/product/product_id/2885158/top","extras":{},"createdAt":"2011-04-15
            02: 31: 17","updatedAt":"2011-04-15 02: 31: 17","publishedAt":"2011-04-15 02: 31: 17","expiredAt":"0000-00-00
00: 00: 00"},{"class":"product_like","id":"2885158: 100050515","owner":{"class":"uid","id":"100050515","owner":null,"parent":null,"label":"CRUELLA","description":"","image":{"url":"https: //fitter.cosme.net/images/user/characters/150/mychara02_xl.gif"},"url":"https://www.cosme.net/user/100050515","extras":{"coverImage":{"url":"https://fitter.cosme.net/images/user/covers/mycover_skincare.jpg"}},"createdAt":"2001-06-09
            17: 31: 10","updatedAt":"2018-03-15 09: 48: 02","publishedAt":"2017-12-29 10: 04: 26","expiredAt":"0000-00-00
00: 00: 00"},"parent":{"class":"product","id":"2885158","owner":null,"parent":{"class":"brand","id":"515","owner":null,"parent":null,"label":"ビューティーネイラー","description":"","image":{"url":""},"url":"https: //www.cosme.net/brand/brand_id/515/top/nt","extras":{"hasContract":false},"createdAt":"2000-03-27
            13: 20: 25","updatedAt":"2010-09-15 09: 50: 57","publishedAt":"2000-03-27 13: 20: 25","expiredAt":"0000-00-00
00: 00: 00"},"label":"アイラッシュバリューパック","description":"ボリュームと長さをアップしてインパクトのある目元に仕上げます。つけまつ毛が５ペア入ったバリューパック。水洗いしてくり返し使えます。\r\n【セット内容】\r\nつけまつ毛×5ペア\r\nまつげ強力接着剤×1本\r\n単品サイズ：縦142×横幅85×奥行14(mm)","image":{"url":"https: //fitter.cosme.net/media/product/2885/skuimg_753333_xl.jpg"},"url":"https://www.cosme.net/product/product_id/2885158/top","extras":{"categories":[{"id":"1114","label":"つけまつげ"}]},"createdAt":"2005-12-19
            23: 46: 50","updatedAt":"2020-03-27 13: 40: 38","publishedAt":"2020-03-27 13: 41: 09","expiredAt":"0000-00-00
00: 00: 00"},"label":"","description":"","image":{"url":""},"url":"https: //www.cosme.net/product/product_id/2885158/top","extras":{},"createdAt":"2011-05-10
            17: 43: 03","updatedAt":"2011-05-10 17: 43: 03","publishedAt":"2011-05-10 17: 43: 03","expiredAt":"0000-00-00
00: 00: 00"},{"class":"product_like","id":"2885158: 100056969","owner":{"class":"uid","id":"100056969","owner":null,"parent":null,"label":"すいか。","description":"","image":{"url":"https: //fitter.cosme.net/media/collection/13/3721/7706549.jpg"},"url":"https://www.cosme.net/user/100056969","extras":{"coverImage":{"url":"https://fitter.cosme.net/images/user/covers/mycover_nail.jpg"}},"createdAt":"2001-08-17
            10: 44: 31","updatedAt":"2021-03-19 23: 03: 08","publishedAt":"2017-12-20 11: 31: 39","expiredAt":"0000-00-00
00: 00: 00"},"parent":{"class":"product","id":"2885158","owner":null,"parent":{"class":"brand","id":"515","owner":null,"parent":null,"label":"ビューティーネイラー","description":"","image":{"url":""},"url":"https: //www.cosme.net/brand/brand_id/515/top/nt","extras":{"hasContract":false},"createdAt":"2000-03-27
            13: 20: 25","updatedAt":"2010-09-15 09: 50: 57","publishedAt":"2000-03-27 13: 20: 25","expiredAt":"0000-00-00
00: 00: 00"},"label":"アイラッシュバリューパック","description":"ボリュームと長さをアップしてインパクトのある目元に仕上げます。つけまつ毛が５ペア入ったバリューパック。水洗いしてくり返し使えます。\r\n【セット内容】\r\nつけまつ毛×5ペア\r\nまつげ強力接着剤×1本\r\n単品サイズ：縦142×横幅85×奥行14(mm)","image":{"url":"https: //fitter.cosme.net/media/product/2885/skuimg_753333_xl.jpg"},"url":"https://www.cosme.net/product/product_id/2885158/top","extras":{"categories":[{"id":"1114","label":"つけまつげ"}]},"createdAt":"2005-12-19
            23: 46: 50","updatedAt":"2020-03-27 13: 40: 38","publishedAt":"2020-03-27 13: 41: 09","expiredAt":"0000-00-00
00: 00: 00"},"label":"","description":"","image":{"url":""},"url":"https: //www.cosme.net/product/product_id/2885158/top","extras":{},"createdAt":"2012-02-24
            21: 33: 24","updatedAt":"2016-09-30 15: 38: 04","publishedAt":"2012-02-24 21: 33: 24","expiredAt":"0000-00-00 00: 00: 00"}]